{"1000":{"r":"Skopje","c":"Skopje"},"1011":{"r":"Cucer Sandevo","c":"Chucher - Sandevo"},"1040":{"r":"Skopje","c":"Skopje"},"1041":{"r":"Ilinden","c":"Kadino"},"1043":{"r":"Petrovec","c":"Petrovec"},"1045":{"r":"Aracinovo","c":"Arachinovo"},"1053":{"r":"Studenicani","c":"Studenichani"},"1063":{"r":"Skopje","c":"Bukovik"},"1200":{"r":"Tetovo","c":"Tetovo"},"1211":{"r":"Tearce","c":"Dobroste"},"1212":{"r":"Tetovo","c":"Dzepciste"},"1215":{"r":"Jegunovce","c":"Jegunovce"},"1216":{"r":"Brvenica","c":"Brvenica"},"1218":{"r":"Zelino","c":"Sedlarevo"},"1219":{"r":"Tetovo","c":"Golema Recica"},"1220":{"r":"Bogovinje","c":"Bogovinje"},"1221":{"r":"Bogovinje","c":"Kamenjane"},"1224":{"r":"Tearce","c":"Prsovce"},"1225":{"r":"Jegunovce","c":"Vratnica"},"1226":{"r":"Zelino","c":"Strimnica"},"1230":{"r":"Gostivar","c":"Gostivar"},"1236":{"r":"Vrapciste","c":"Negotino"},"1238":{"r":"Vrapciste","c":"Vrapciste"},"1250":{"r":"Debar","c":"Debar"},"1254":{"r":"Mavrovo i Rostusa","c":"Rostusha"},"1258":{"r":"Centar Zupa","c":"Centar Zupa"},"1300":{"r":"Kumanovo","c":"Kumanovo"},"1306":{"r":"Lipkovo","c":"Matejche"},"1324":{"r":"Lipkovo","c":"Lojane"},"1330":{"r":"Kriva Palanka","c":"Kriva Palanka"},"1360":{"r":"Kratovo","c":"Kratovo"},"1400":{"r":"Veles","c":"Veles"},"1414":{"r":"Novo Selo","c":"Novo Selo"},"1420":{"r":"Gradsko","c":"Gradsko"},"1430":{"r":"Kavadarci","c":"Kavadarci"},"1440":{"r":"Negotino","c":"Negotino"},"1442":{"r":"Demir Kapija","c":"Demir Kapija"},"1480":{"r":"Gevgelija","c":"Gevgelija"},"1484":{"r":"Bogdanci","c":"Bogdanci"},"1489":{"r":"Gevgelija","c":"Miravci"},"2000":{"r":"Stip","c":"Shtip"},"2210":{"r":"Probistip","c":"Probishtip"},"2212":{"r":"Probistip","c":"Zletovo"},"2220":{"r":"Sveti Nikole","c":"Sveti Nikole"},"2300":{"r":"Kocani","c":"Kochani"},"2301":{"r":"Cesinovo-Oblesevo","c":"Obleshevo"},"2302":{"r":"Kocani","c":"Orizari"},"2304":{"r":"Makedonska Kamenica","c":"Makedonska Kamenica"},"2310":{"r":"Vrapciste","c":"Gradec"},"2314":{"r":"Vinica","c":"Blatec"},"2315":{"r":"Berovo","c":"Rusinovo"},"2320":{"r":"Delcevo","c":"Delchevo"},"2326":{"r":"Pehcevo","c":"Pehcevo"},"2330":{"r":"Berovo","c":"Berovo"},"2333":{"r":"Cesinovo-Oblesevo","c":"Cesinovo"},"2400":{"r":"Strumica","c":"Strumica"},"2410":{"r":"Strumica","c":"Kuklish"},"2411":{"r":"Vasilevo","c":"Vasilevo"},"2414":{"r":"Strumica","c":"Velusa"},"2420":{"r":"Radovis","c":"Radovish"},"2423":{"r":"Radovis","c":"Podares"},"2431":{"r":"Bosilovo","c":"Bosilovo"},"2435":{"r":"Novo Selo","c":"Novo Selo"},"2460":{"r":"Valandovo","c":"Valandovo"},"6250":{"r":"Kicevo","c":"Kicevo"},"6253":{"r":"Skopje","c":"Zajas"},"6254":{"r":"Skopje","c":"Tuin"},"6322":{"r":"Ohrid","c":"Ohrid"},"6330":{"r":"Struga","c":"Struga"},"6334":{"r":"Struga","c":"Velesta"},"6335":{"r":"Vevcani","c":"Vevcani"},"6336":{"r":"Struga","c":"Labunishta"},"6342":{"r":"Struga","c":"Delogozda"},"6530":{"r":"Makedonski Brod","c":"Makedonski Brod"},"7000":{"r":"Bitola","c":"Bitola"},"7221":{"r":"Bitola","c":"Bistrica"},"7240":{"r":"Demir Hisar","c":"Demir Hisar"},"7241":{"r":"Bitola","c":"Kukurecani"},"7244":{"r":"Demir Hisar","c":"Sopotnica"},"7310":{"r":"Resen","c":"Resen"},"7313":{"r":"Bitola","c":"Capari"},"7316":{"r":"Resen","c":"Grncari"},"7317":{"r":"Resen","c":"Krani"},"7500":{"r":"Prilep","c":"Prilep"},"7504":{"r":"Dolneni","c":"Desovo"},"7507":{"r":"Dolneni","c":"Lazani"},"7550":{"r":"Krusevo","c":"Krushevo"},"":{"r":"","c":""}}