{"id":"AF","country":"Afghanistan","postal":{"10":{"code":"10","region":"Kabul","city":"Kabul","latitude":34.52813,"longitude":69.17233},"15":{"code":"15","region":"Kabul","city":"Kabul","latitude":34.52813,"longitude":69.17233},"38":{"code":"38","region":"Kabul","city":"Kabul","latitude":34.52813,"longitude":69.17233},"40":{"code":"40","region":"Kabul","city":"Kabul","latitude":34.52813,"longitude":69.17233},"193":{"code":"193","region":"Kabul","city":"Kabul","latitude":34.52813,"longitude":69.17233},"357":{"code":"357","region":"Kabul","city":"Kabul","latitude":34.52813,"longitude":69.17233},"700":{"code":"700","region":"Kabul","city":"Kabul","latitude":34.52813,"longitude":69.17233},"959":{"code":"959","region":"Kabul","city":"Kabul","latitude":34.52813,"longitude":69.17233},"1001":{"code":"1001","region":"Kabul","city":"Kabul","latitude":34.52813,"longitude":69.17233},"1064":{"code":"1064","region":"Kabul","city":"Paghman","latitude":34.5875,"longitude":68.95333},"1101":{"code":"1101","region":"Parwan","city":"Charikar","latitude":35.01361,"longitude":69.17139},"1701":{"code":"1701","region":"Balkh","city":"Mazar-e Sharif","latitude":36.70904,"longitude":67.11087},"1901":{"code":"1901","region":"Jowzjan","city":"Shibirghan","latitude":36.66757,"longitude":65.7529},"2201":{"code":"2201","region":"Paktiya","city":"Gardez","latitude":33.59744,"longitude":69.22592},"2460":{"code":"2460","region":"Paktika","city":"Markaz-e Wuluswali-ye Yosuf Khel","latitude":33.06455,"longitude":68.67084},"2501":{"code":"2501","region":"Khost","city":"Khost","latitude":33.33951,"longitude":69.92041},"2601":{"code":"2601","region":"Nangarhar","city":"Jalalabad","latitude":34.42647,"longitude":70.45153},"3001":{"code":"3001","region":"Herat","city":"Herat","latitude":34.34817,"longitude":62.19967},"3021":{"code":"3021","region":"Kabul","city":"Kabul","latitude":34.52813,"longitude":69.17233},"3201":{"code":"3201","region":"Ghor","city":"Chaghcharan","latitude":34.51952,"longitude":65.25094},"3451":{"code":"3451","region":"Badakhshan","city":"'Alaqahdari-ye Kiran wa Munjan","latitude":36.02866,"longitude":70.77258},"3501":{"code":"3501","region":"Kunduz","city":"Kunduz","latitude":36.72896,"longitude":68.857},"3601":{"code":"3601","region":"Baghlan","city":"Pul-e Khumri","latitude":35.94458,"longitude":68.71512},"3801":{"code":"3801","region":"Kandahar","city":"Kandahar","latitude":31.61332,"longitude":65.71013},"3961":{"code":"3961","region":"Helmand","city":"Hukumat-e Nad 'Ali","latitude":31.64286,"longitude":64.23982},"4101":{"code":"4101","region":"Uruzgan","city":"Tarinkot","latitude":32.62675,"longitude":65.87331},"4301":{"code":"4301","region":"Nimroz","city":"Zaranj","latitude":30.96667,"longitude":61.88333},"":{"code":"","region":"","city":"","latitude":34.52813,"longitude":69.17233}}}